{
  "ADAINR": {
    "coin": "ADAINR",
    "allTimeHigh": 236
  },
  "ATOMINR": {
    "coin": "ATOMINR",
    "allTimeHigh": 3590
  },
  "AVAXINR": {
    "coin": "AVAXINR",
    "allTimeHigh": 11900
  },
  "AXSINR": {
    "coin": "AXSINR",
    "allTimeHigh": 13500
  },
  "BABYDOGEINR": {
    "coin": "BABYDOGEINR",
    "allTimeHigh": 0
  },

  "BNBINR": {
    "coin": "BNBINR",
    "allTimeHigh": 54000
  },
  "BRISEINR": {
    "coin": "BRISEINR",
    "allTimeHigh": 0.0001418
  },
  "BTCINR": {
    "coin": "BTCINR",
    "allTimeHigh": 5855000
  },
  "BTTCINR": {
    "coin": "BTTCINR",
    "allTimeHigh": 0.0002558
  },
  "CATEINR": {
    "coin": "CATEINR",
    "allTimeHigh": 0
  },
  "CELRINR": {
    "coin": "CELRINR",
    "allTimeHigh": 14.8108
  },
  "DOGEINR": {
    "coin": "DOGEINR",
    "allTimeHigh": 58.38
  },
  "DOTINR": {
    "coin": "DOTINR",
    "allTimeHigh": 4397
  },
  "ELONINR": {
    "coin": "ELONINR",
    "allTimeHigh": 0
  },
  "ENJINR": {
    "coin": "ENJINR",
    "allTimeHigh": 372
  },
  "ETHINR": {
    "coin": "ETHINR",
    "allTimeHigh": 384899
  },
  "FILINR": {
    "coin": "FILINR",
    "allTimeHigh": 17632
  },
  "FRONTINR": {
    "coin": "FRONTINR",
    "allTimeHigh": 300
  },
  "FTMINR": {
    "coin": "FTMINR",
    "allTimeHigh": 277
  },
  "GALAINR": {
    "coin": "GALAINR",
    "allTimeHigh": 53.6
  },
  "HBARINR": {
    "coin": "HBARINR",
    "allTimeHigh": 33.94
  },
  "IOTXINR": {
    "coin": "IOTXINR",
    "allTimeHigh": 18.72
  },
  "MANAINR": {
    "coin": "MANAINR",
    "allTimeHigh": 452
  },
  "MATICINR": {
    "coin": "MATICINR",
    "allTimeHigh": 229
  },
  "POLYINR": {
    "coin": "POLYINR",
    "allTimeHigh": 0
  },
  "QUACKINR": {
    "coin": "QUACKINR",
    "allTimeHigh": 0
  },
  "RENINR": {
    "coin": "RENINR",
    "allTimeHigh": 125
  },
  "SOLINR": {
    "coin": "SOLINR",
    "allTimeHigh": 20800
  },
  "SHIBINR": {
    "coin": "SHIBINR",
    "allTimeHigh": 0.009
  },
  "TRXINR": {
    "coin": "TRXINR",
    "allTimeHigh": 12
  },
  "VETINR": {
    "coin": "VETINR",
    "allTimeHigh": 25
  },
  "WRXINR": {
    "coin": "WRXINR",
    "allTimeHigh": 0
  },
  "XLMINR": {
    "coin": "XLMINR",
    "allTimeHigh": 65
  },
  "XRPINR": {
    "coin": "XRPINR",
    "allTimeHigh": 155
  },
  "runeINR": {
    "coin": "runeINR",
    "allTimeHigh": 1349
  },
  "LINKINR": {
    "coin": "LINKINR",
    "allTimeHigh": 4166
  },
  "KISHUINR": {
    "coin": "KISHUINR",
    "allTimeHigh": 0
  },
  "POLYDOGEINR": {
    "coin": "POLYDOGEINR",
    "allTimeHigh": 0
  },
  "SAITAMAINR": {
    "coin": "SAITAMAINR",
    "allTimeHigh": 0
  },
  "KINGSHIBINR": {
    "coin": "KINGSHIBINR",
    "allTimeHigh": 0
  },
  "SFMINR": {
    "coin": "SFMINR",
    "allTimeHigh": 0
  },
  "ATLASINR": {
    "coin": "ATLASINR",
    "allTimeHigh": 0
  },
  "UFOINR": {
    "coin": "UFOINR",
    "allTimeHigh": 0
  },
  "PIXELINR": {
    "coin": "PIXELINR",
    "allTimeHigh": 0
  },
  "MIMIRINR": {
    "coin": "MIMIRINR",
    "allTimeHigh": 0
  },
  "EVERGROWINR": {
    "coin": "EVERGROWINR",
    "allTimeHigh": 0
  },
  "JAIHOINR": {
    "coin": "JAIHOINR",
    "allTimeHigh": 0
  },
  "ACHINR": {
    "coin": "ACHINR",
    "allTimeHigh": 12
  },
  "CAKEINR": {
    "coin": "CAKEINR",
    "allTimeHigh": 2050
  },
  "TWTINR": {
    "coin": "TWTINR",
    "allTimeHigh": 0
  }
}
